hesab.py
hesab-0.2.0.dist-info/entry_points.txt
hesab-0.2.0.dist-info/LICENSE
hesab-0.2.0.dist-info/WHEEL
hesab-0.2.0.dist-info/METADATA
hesab-0.2.0.dist-info/RECORD
