Metadata-Version: 2.1
Name: hesab
Version: 0.2.0
Summary: A CLI personal accounting app with Persian calendar
Keywords: Accounting,persian
Author-email: Erfan Kheyrollahi Qaroğlu <ekm507@gmail.com>
Requires-Python: >=3.9
Classifier: Programming Language :: Python :: 3
Classifier: License :: OSI Approved :: GNU General Public License v3 or later (GPLv3+)
Classifier: Operating System :: OS Independent
Requires-Dist: click
Requires-Dist: jdatetime
Requires-Dist: rich
Project-URL: Bug Tracker, https://github.com/ekm507/hesab/issues
Project-URL: Homepage, https://github.com/ekm507/hesab
Project-URL: Source Code, https://github.com/ekm507/hesab
